h3-3.7.7.data/data/setup.py
h3-3.7.7.data/data/LICENSE
h3-3.7.7.data/data/requirements.in
h3-3.7.7.data/data/pyproject.toml
h3-3.7.7.data/data/CHANGELOG.md
h3-3.7.7.data/data/readme.md
h3-3.7.7.data/data/makefile
h3-3.7.7.data/data/CMakeLists.txt
h3-3.7.7.data/data/src/h3lib/LICENSE
h3-3.7.7.data/data/src/h3lib/README.md
h3-3.7.7.data/data/src/h3lib/VERSION
h3-3.7.7.data/data/src/h3lib/CMakeLists.txt
h3-3.7.7.data/data/src/h3lib/cmake/Config.cmake.in
h3-3.7.7.data/data/src/h3lib/cmake/toolchain.cmake
h3-3.7.7.data/data/src/h3lib/cmake/TestWrapValgrind.cmake
h3-3.7.7.data/data/src/h3lib/examples/neighbors.c
h3-3.7.7.data/data/src/h3lib/examples/distance.c
h3-3.7.7.data/data/src/h3lib/examples/index.c
h3-3.7.7.data/data/src/h3lib/examples/compact.c
h3-3.7.7.data/data/src/h3lib/examples/edge.c
h3-3.7.7.data/data/src/h3lib/examples/CMakeLists.txt
h3-3.7.7.data/data/src/h3lib/src/h3lib/include/alloc.h
h3-3.7.7.data/data/src/h3lib/src/h3lib/include/localij.h
h3-3.7.7.data/data/src/h3lib/src/h3lib/include/faceijk.h
h3-3.7.7.data/data/src/h3lib/src/h3lib/include/h3UniEdge.h
h3-3.7.7.data/data/src/h3lib/src/h3lib/include/coordijk.h
h3-3.7.7.data/data/src/h3lib/src/h3lib/include/vertexGraph.h
h3-3.7.7.data/data/src/h3lib/src/h3lib/include/vec2d.h
h3-3.7.7.data/data/src/h3lib/src/h3lib/include/vec3d.h
h3-3.7.7.data/data/src/h3lib/src/h3lib/include/polygonAlgos.h
h3-3.7.7.data/data/src/h3lib/src/h3lib/include/algos.h
h3-3.7.7.data/data/src/h3lib/src/h3lib/include/linkedGeo.h
h3-3.7.7.data/data/src/h3lib/src/h3lib/include/polygon.h
h3-3.7.7.data/data/src/h3lib/src/h3lib/include/h3Index.h
h3-3.7.7.data/data/src/h3lib/src/h3lib/include/bbox.h
h3-3.7.7.data/data/src/h3lib/src/h3lib/include/vertex.h
h3-3.7.7.data/data/src/h3lib/src/h3lib/include/baseCells.h
h3-3.7.7.data/data/src/h3lib/src/h3lib/include/h3api.h.in
h3-3.7.7.data/data/src/h3lib/src/h3lib/include/constants.h
h3-3.7.7.data/data/src/h3lib/src/h3lib/include/mathExtensions.h
h3-3.7.7.dist-info/LICENSE
h3-3.7.7.dist-info/RECORD
h3-3.7.7.dist-info/METADATA
h3-3.7.7.dist-info/WHEEL
h3-3.7.7.dist-info/top_level.txt
